{
  "pera" : {
    "username" : "pera",
    "password" : "pera",
    "name" : "Petar",
    "surname" : "Petric",
    "gender" : "MALE",
    "userType" : "BUYER",
    "dateOfBirth" : "2000-01-03",
    "blocked" : false,
    "points" : 226.765,
    "typeBuyer" : {
      "name" : "Bronzani",
      "discount" : 10,
      "requiredPointsForNext" : 300
    },
    "orders" : [ {
      "id" : "PpQqEDrfI7",
      "itemsInCart" : [ {
        "item" : {
          "name" : "Kola",
          "price" : 100.0,
          "type" : "pi\u0107e",
          "restaurantName" : "Djava",
          "quantity" : "",
          "description" : "",
          "image" : "res/images/restaurants/Djava/Kola/kola.jpg",
          "deleted" : false
        },
        "quantity" : 2
      }, {
        "item" : {
          "name" : "Pomfrit",
          "price" : 100.0,
          "type" : "jelo",
          "restaurantName" : "Djava",
          "quantity" : "200g",
          "description" : "",
          "image" : "res/images/restaurants/Djava/Pomfrit/pomes.jpg",
          "deleted" : false
        },
        "quantity" : 2
      }, {
        "item" : {
          "name" : "Pljeskavica",
          "price" : 200.0,
          "type" : "jelo",
          "restaurantName" : "Djava",
          "quantity" : "150g",
          "description" : "",
          "image" : "res/images/restaurants/Djava/Pljeskavica/pljeska.jpg",
          "deleted" : false
        },
        "quantity" : 2
      } ],
      "restaurantName" : "Djava",
      "dateTime" : "2021.09.10 19:28:37",
      "price" : 800.0,
      "nameSurname" : "Petar Petric",
      "location" : {
        "longitude" : null,
        "latitude" : null,
        "street" : "Pere peric",
        "number" : "1",
        "place" : "NS",
        "postalCode" : "21000",
        "address" : null
      },
      "orderStatus" : "CANCELED",
      "usernameDeliveryMan" : ""
    }, {
      "id" : "P8jeYYhY9r",
      "itemsInCart" : [ {
        "item" : {
          "name" : "Kola",
          "price" : 100.0,
          "type" : "pi\u0107e",
          "restaurantName" : "Djava",
          "quantity" : "",
          "description" : "",
          "image" : "res/images/restaurants/Djava/Kola/kola.jpg",
          "deleted" : false
        },
        "quantity" : 4
      }, {
        "item" : {
          "name" : "Pomfrit",
          "price" : 100.0,
          "type" : "jelo",
          "restaurantName" : "Djava",
          "quantity" : "200g",
          "description" : "",
          "image" : "res/images/restaurants/Djava/Pomfrit/pomes.jpg",
          "deleted" : false
        },
        "quantity" : 4
      }, {
        "item" : {
          "name" : "Pljeskavica",
          "price" : 200.0,
          "type" : "jelo",
          "restaurantName" : "Djava",
          "quantity" : "150g",
          "description" : "",
          "image" : "res/images/restaurants/Djava/Pljeskavica/pljeska.jpg",
          "deleted" : false
        },
        "quantity" : 4
      } ],
      "restaurantName" : "Djava",
      "dateTime" : "2021.09.10 19:30:45",
      "price" : 1600.0,
      "nameSurname" : "Petar Petric",
      "location" : {
        "longitude" : null,
        "latitude" : null,
        "street" : "Voj.",
        "number" : "2",
        "place" : "NS",
        "postalCode" : "21000",
        "address" : null
      },
      "orderStatus" : "DELIVERED",
      "usernameDeliveryMan" : "din"
    }, {
      "id" : "PyLF4zexGe",
      "itemsInCart" : [ {
        "item" : {
          "name" : "Pasulj",
          "price" : 200.0,
          "type" : "Jelo",
          "restaurantName" : "Kutlaca Bar",
          "quantity" : "400ml",
          "description" : "",
          "image" : "res/images/restaurants/Kutlaca Bar/Pasulj/pasulj.jpg",
          "deleted" : false
        },
        "quantity" : 2
      }, {
        "item" : {
          "name" : "Gulas",
          "price" : 300.0,
          "type" : "Jelo",
          "restaurantName" : "Kutlaca Bar",
          "quantity" : "400ml",
          "description" : "",
          "image" : "res/images/restaurants/Kutlaca Bar/Gulas/gulas.jpg",
          "deleted" : false
        },
        "quantity" : 4
      }, {
        "item" : {
          "name" : "Krempita",
          "price" : 100.0,
          "type" : "Kola\u010D",
          "restaurantName" : "Kutlaca Bar",
          "quantity" : "150g",
          "description" : "",
          "image" : "res/images/restaurants/Kutlaca Bar/Krempita/krempita.jpg",
          "deleted" : false
        },
        "quantity" : 5
      } ],
      "restaurantName" : "Kutlaca Bar",
      "dateTime" : "2021.09.10 19:34:51",
      "price" : 2100.0,
      "nameSurname" : "Petar Petric",
      "location" : {
        "longitude" : null,
        "latitude" : null,
        "street" : "Voj.",
        "number" : "3",
        "place" : "NS",
        "postalCode" : "21000",
        "address" : null
      },
      "orderStatus" : "DELIVERED",
      "usernameDeliveryMan" : "din"
    }, {
      "id" : "PhLuukkVDJ",
      "itemsInCart" : [ {
        "item" : {
          "name" : "Pica",
          "price" : 200.0,
          "type" : "jelo",
          "restaurantName" : "Macak",
          "quantity" : "30cm",
          "description" : "",
          "image" : "res/images/restaurants/Macak/Pica/pica.jpg",
          "deleted" : false
        },
        "quantity" : 2
      }, {
        "item" : {
          "name" : "Voda",
          "price" : 50.0,
          "type" : "pi\u0107e",
          "restaurantName" : "Macak",
          "quantity" : "",
          "description" : "rosa",
          "image" : "res/images/restaurants/Macak/Voda/rosa.jpg",
          "deleted" : false
        },
        "quantity" : 1
      } ],
      "restaurantName" : "Macak",
      "dateTime" : "2021.09.10 19:38:59",
      "price" : 405.0,
      "nameSurname" : "Petar Petric",
      "location" : {
        "longitude" : null,
        "latitude" : null,
        "street" : "Voj.",
        "number" : "2",
        "place" : "NS",
        "postalCode" : "21000",
        "address" : null
      },
      "orderStatus" : "DELIVERED",
      "usernameDeliveryMan" : "din"
    } ],
    "cart" : {
      "username" : "pera",
      "itemsInCart" : [ ],
      "price" : 0.0
    }
  }
}